django_modelqueryform-1.0.0.dist-info/RECORD
django_modelqueryform-1.0.0.dist-info/DESCRIPTION.rst
django_modelqueryform-1.0.0.dist-info/metadata.json
django_modelqueryform-1.0.0.dist-info/top_level.txt
django_modelqueryform-1.0.0.dist-info/WHEEL
django_modelqueryform-1.0.0.dist-info/METADATA
modelqueryform/forms.py
modelqueryform/__init__.py
modelqueryform/utils.py
modelqueryform/widgets.py
