Metadata-Version: 2.0
Name: django-modelqueryform
Version: 1.0.0
Summary: App for generating forms allowing users to build model queries
Home-page: https://github.com/ckirby/django-modelqueryform
Author: Chaim Kirby
Author-email: chaim.kirby@gmail.com
License: BSD
Keywords: django-modelqueryform
Platform: UNKNOWN
Classifier: Development Status :: 5 - Production/Stable
Classifier: Framework :: Django
Classifier: Intended Audience :: Developers
Classifier: License :: OSI Approved :: BSD License
Classifier: Natural Language :: English
Classifier: Programming Language :: Python :: 2
Classifier: Programming Language :: Python :: 2.7
Classifier: Programming Language :: Python :: 3
Classifier: Programming Language :: Python :: 3.3
